etcd_watcher/__init__.py
etcd_watcher/watcher.py
tests/__init__.py
tests/test_etcd_watcher.py
testtesttest00000000-1.0.3.dist-info/LICENSE
testtesttest00000000-1.0.3.dist-info/METADATA
testtesttest00000000-1.0.3.dist-info/WHEEL
testtesttest00000000-1.0.3.dist-info/top_level.txt
testtesttest00000000-1.0.3.dist-info/RECORD
